{
  "version": "7",
  "dialect": "postgresql",
  "entries": [
    {
      "idx": 0,
      "version": "7",
      "when": 1771496233843,
      "tag": "0000_same_pandemic",
      "breakpoints": true
    },
    {
      "idx": 1,
      "version": "7",
      "when": 1771496862782,
      "tag": "0001_acoustic_quasimodo",
      "breakpoints": true
    },
    {
      "idx": 2,
      "version": "7",
      "when": 1771925737250,
      "tag": "0002_wooden_roulette",
      "breakpoints": true
    },
    {
      "idx": 3,
      "version": "7",
      "when": 1772099870552,
      "tag": "0003_silky_solo",
      "breakpoints": true
    }
  ]
}